{"id":"nonfinancial_risks_nfr_in_defi","name":"Non-financial risks (NFR) in DeFi","description":"This session will be held in English. There will be no translation to Italian.","start":"2023-05-24T12:30:00.000Z","end":"2023-05-24T12:55:00.000Z","stageId":"volcano_stage","speakers":[{"id":"nikita_buzov","name":"Nikita Buzov","bio":"Solace DAO","eventId":"spagetteth_naples","photo":"https://naples.spaghett-eth.com/images/speakers/nikitaBuzov.jpeg"}],"videoUrl":"https://lp-playback.com/hls/ec3bw6cpqcr4se7o/index.m3u8","playbackId":"ec3bw6cpqcr4se7o","eventId":"spagetteth_naples"}