{"id":"132","name":"Biotesting and how to guide your longevity focused actions","description":"- 5-min meditation session /\n- Mike Geer - Biotesting and how to guide your longevity focused actions (5-10min) /\n- Adam Gries - longevity jurisdictions/network states, politics (5-10min) /\n- Fishbowl discussion (~45min)","track":"Longevity 0-1","stage":{"id":"5","name":"Dome"},"start":1680278400000,"end":1680282000000,"speakers":[{"id":"Adam Gries","name":"Adam Gries"},{"id":"Mike Geer","name":"Mike Geer"}]}