{"id":"636","name":"Network States Part II","description":"<p>2:00pm - 2:20pm: Laurence Ion, VitaDAO -  Creating a Longevity Network State 2:20pm - 2:40pm: Kristof de Spiegeleer Threefold -  Network State Infra from Zanzibar Free Zone<br>\n2:40pm - 3:00pm: Kosta Korenkov Montelibro - Free Society Project In Europe</p>","track":"New Cities & Network States","stage":{"id":"Dome","name":"Dome","stream":[{"id":"dd91a031-33e3-4567-aa35-d8df14a030f4"}]},"start":1682942400000,"end":1682946000000,"speakers":[{"id":"Niklas Anzinger","name":"Niklas Anzinger"}]}